{
  "appPageId" : "41c3239d-0aff-458c-8a72-49e9ba067b44",
  "componentName" : "siteforce:sldsOneColLayout",
  "id" : "4a5359fd-2b45-41e3-8845-849c8788bf47",
  "label" : "Record List",
  "regions" : [ {
    "id" : "63c790e3-d720-4efb-a64f-d6741a2ff5bc",
    "regionName" : "header",
    "type" : "region"
  }, {
    "components" : [ {
      "componentAttributes" : {
        "enableInlineEdit" : false,
        "filterName" : "{!filterId}",
        "layout" : "FULL",
        "pageSize" : 25,
        "scope" : "{!objectName}",
        "showActionBar" : false,
        "showChartsPanel" : false,
        "showDisplay" : "grid",
        "showFilterPanel" : true,
        "showImageIcon" : true,
        "showManualRefreshButton" : true,
        "showObjectName" : true,
        "showPinnedList" : true,
        "showSearchBar" : true
      },
      "componentName" : "forceCommunity:objectHome",
      "id" : "c7019733-2e75-4924-9e93-811c6f3d80e1",
      "renderPriority" : "NEUTRAL",
      "renditionMap" : { },
      "type" : "component"
    } ],
    "id" : "98e10adb-eaaa-4295-9e24-4bc6af5417ce",
    "regionName" : "content",
    "type" : "region"
  }, {
    "id" : "66bb81a3-de32-4094-affc-4f5b8660f1a0",
    "regionName" : "footer",
    "type" : "region"
  } ],
  "themeLayoutType" : "Inner",
  "type" : "view",
  "viewType" : "list"
}